README.rst
setup.py
httpdns/__init__.py
httpdns.egg-info/PKG-INFO
httpdns.egg-info/SOURCES.txt
httpdns.egg-info/dependency_links.txt
httpdns.egg-info/requires.txt
httpdns.egg-info/top_level.txt