Metadata-Version: 1.1
Name: httpdns
Version: 0.1.0
Summary: Get host's IP by D+ of DNSPod.
Home-page: http://github.com/codeif/httpdns
Author: codeif
Author-email: me@codeif.com
License: MIT
Platform: UNKNOWN
Classifier: Programming Language :: Python :: 2
Classifier: Programming Language :: Python :: 3
